catsay/__init__.py
catsay/cat.py
catsay-1.0.4.dist-info/LICENSE
catsay-1.0.4.dist-info/METADATA
catsay-1.0.4.dist-info/WHEEL
catsay-1.0.4.dist-info/top_level.txt
catsay-1.0.4.dist-info/RECORD
