Metadata-Version: 2.1
Name: catsay
Version: 1.0.4
Summary: A python package for no one.
Home-page: https://github.com/tikendraw/catsay
Author: tikendraw
Author-email: tikendraksahu1029@gmail.com
Project-URL: Bug Tracker, https://github.com/tikendraw/catsay/issues
License-File: LICENSE
